{
    "switch_mc_info": {
        "ivid": 1001
    }, 
    "switch_mld_info": {
        "bvid": 4000, 
        "ivid": 2001, 
        "pbb_isid": 10001
    }, 
    "switches": [
        {
            "_comment": "エッジスイッチ", 
            "_container_sw_ports(comment)": "収容スイッチとの接続ポート", 
            "_edge_router_port(comment)": "エッジルータとの接続ポート", 
            "_mld_port(comment)": "MLD処理部との接続ポート", 
            "container_sw_ports": [
                49, 
                50
            ], 
            "datapathid": 276595101184, 
            "edge_router_port": 2, 
            "mld_port": 1, 
            "sw_bmac": "00:40:66:5a:4e:00", 
            "sw_name": "esw", 
            "sw_type": 12000
        }, 
        {
            "_comment": "収容スイッチ1", 
            "_edge_switch_port(comment)": "エッジスイッチとの接続ポート", 
            "_olt_ports(comment)": "OLTとの接続ポート", 
            "datapathid": 276596903168, 
            "edge_switch_port": 50, 
            "olt_ports": [
                1
            ], 
            "sw_bmac": "02:40:66:75:cd:00", 
            "sw_name": "sw1", 
            "sw_type": 12000
        }, 
        {
            "_comment": "収容スイッチ2", 
            "_edge_switch_port(comment)": "エッジスイッチとの接続ポート", 
            "_olt_ports(comment)": "OLTとの接続ポート", 
            "datapathid": 276596902016, 
            "edge_switch_port": 50, 
            "olt_ports": [
                1
            ], 
            "sw_bmac": "02:40:66:75:c8:80", 
            "sw_name": "sw2", 
            "sw_type": 12000
        }
    ]
}